{
    "Meta Data": {
        "1. Information": "Intraday (5min) open, high, low, close prices and volume",
        "2. Symbol": "AMZN",
        "3. Last Refreshed": "2022-06-07 20:00:00",
        "4. Interval": "5min",
        "5. Output Size": "Compact",
        "6. Time Zone": "US/Eastern"
    },
    "Time Series (5min)": {
        "2022-06-07 20:00:00": {
            "1. open": "122.3500",
            "2. high": "122.4000",
            "3. low": "122.3400",
            "4. close": "122.3700",
            "5. volume": "13663"
        },
        "2022-06-07 19:55:00": {
            "1. open": "122.2800",
            "2. high": "122.4200",
            "3. low": "122.2700",
            "4. close": "122.3500",
            "5. volume": "9849"
        },
        "2022-06-07 19:50:00": {
            "1. open": "122.3900",
            "2. high": "122.4300",
            "3. low": "122.2900",
            "4. close": "122.3900",
            "5. volume": "15529"
        },
        "2022-06-07 19:45:00": {
            "1. open": "122.4300",
            "2. high": "122.4300",
            "3. low": "122.3800",
            "4. close": "122.3800",
            "5. volume": "8123"
        },
        "2022-06-07 19:40:00": {
            "1. open": "122.3800",
            "2. high": "122.4500",
            "3. low": "122.3800",
            "4. close": "122.4000",
            "5. volume": "4072"
        },
        "2022-06-07 19:35:00": {
            "1. open": "122.4000",
            "2. high": "122.4000",
            "3. low": "122.3500",
            "4. close": "122.3800",
            "5. volume": "3526"
        },
        "2022-06-07 19:30:00": {
            "1. open": "122.3300",
            "2. high": "122.4300",
            "3. low": "122.3300",
            "4. close": "122.4100",
            "5. volume": "4721"
        },
        "2022-06-07 19:25:00": {
            "1. open": "122.3300",
            "2. high": "122.3700",
            "3. low": "122.3100",
            "4. close": "122.3700",
            "5. volume": "6478"
        },
        "2022-06-07 19:20:00": {
            "1. open": "122.3100",
            "2. high": "122.3500",
            "3. low": "122.3000",
            "4. close": "122.3500",
            "5. volume": "4859"
        },
        "2022-06-07 19:15:00": {
            "1. open": "122.4000",
            "2. high": "122.4000",
            "3. low": "122.3200",
            "4. close": "122.3200",
            "5. volume": "3843"
        },
        "2022-06-07 19:10:00": {
            "1. open": "122.4000",
            "2. high": "122.4400",
            "3. low": "122.4000",
            "4. close": "122.4400",
            "5. volume": "2977"
        },
        "2022-06-07 19:05:00": {
            "1. open": "122.3500",
            "2. high": "122.4300",
            "3. low": "122.3500",
            "4. close": "122.4300",
            "5. volume": "1772"
        },
        "2022-06-07 19:00:00": {
            "1. open": "122.4300",
            "2. high": "122.4500",
            "3. low": "122.4000",
            "4. close": "122.4000",
            "5. volume": "9554"
        },
        "2022-06-07 18:55:00": {
            "1. open": "122.3800",
            "2. high": "122.4299",
            "3. low": "122.3100",
            "4. close": "122.4100",
            "5. volume": "4675"
        },
        "2022-06-07 18:50:00": {
            "1. open": "122.3500",
            "2. high": "122.4300",
            "3. low": "122.3100",
            "4. close": "122.4300",
            "5. volume": "2868"
        },
        "2022-06-07 18:45:00": {
            "1. open": "122.4700",
            "2. high": "122.4700",
            "3. low": "122.3800",
            "4. close": "122.4000",
            "5. volume": "4471"
        },
        "2022-06-07 18:40:00": {
            "1. open": "122.5000",
            "2. high": "122.5000",
            "3. low": "122.4000",
            "4. close": "122.4000",
            "5. volume": "4619"
        },
        "2022-06-07 18:35:00": {
            "1. open": "122.5000",
            "2. high": "122.5100",
            "3. low": "122.4600",
            "4. close": "122.5000",
            "5. volume": "8518"
        },
        "2022-06-07 18:30:00": {
            "1. open": "122.4300",
            "2. high": "122.4800",
            "3. low": "122.4100",
            "4. close": "122.4700",
            "5. volume": "2527"
        },
        "2022-06-07 18:25:00": {
            "1. open": "122.4600",
            "2. high": "122.4600",
            "3. low": "122.4100",
            "4. close": "122.4100",
            "5. volume": "6274"
        },
        "2022-06-07 18:20:00": {
            "1. open": "122.4500",
            "2. high": "122.4800",
            "3. low": "122.4500",
            "4. close": "122.4800",
            "5. volume": "16950"
        },
        "2022-06-07 18:15:00": {
            "1. open": "122.4300",
            "2. high": "122.4500",
            "3. low": "122.4000",
            "4. close": "122.4000",
            "5. volume": "10483"
        },
        "2022-06-07 18:10:00": {
            "1. open": "122.5800",
            "2. high": "122.5800",
            "3. low": "122.4100",
            "4. close": "122.4500",
            "5. volume": "20736"
        },
        "2022-06-07 18:05:00": {
            "1. open": "122.5200",
            "2. high": "122.6700",
            "3. low": "122.5100",
            "4. close": "122.5800",
            "5. volume": "10414"
        },
        "2022-06-07 18:00:00": {
            "1. open": "122.6000",
            "2. high": "122.6500",
            "3. low": "122.5000",
            "4. close": "122.5100",
            "5. volume": "12558"
        },
        "2022-06-07 17:55:00": {
            "1. open": "122.6000",
            "2. high": "122.6400",
            "3. low": "122.5400",
            "4. close": "122.6000",
            "5. volume": "15920"
        },
        "2022-06-07 17:50:00": {
            "1. open": "122.6800",
            "2. high": "122.6800",
            "3. low": "122.5900",
            "4. close": "122.5900",
            "5. volume": "11779"
        },
        "2022-06-07 17:45:00": {
            "1. open": "122.6800",
            "2. high": "122.6800",
            "3. low": "122.6000",
            "4. close": "122.6800",
            "5. volume": "17475"
        },
        "2022-06-07 17:40:00": {
            "1. open": "122.7000",
            "2. high": "122.7099",
            "3. low": "122.6600",
            "4. close": "122.6600",
            "5. volume": "9200"
        },
        "2022-06-07 17:35:00": {
            "1. open": "122.7300",
            "2. high": "122.7500",
            "3. low": "122.7000",
            "4. close": "122.7000",
            "5. volume": "7938"
        },
        "2022-06-07 17:30:00": {
            "1. open": "122.7398",
            "2. high": "122.7400",
            "3. low": "122.6800",
            "4. close": "122.7001",
            "5. volume": "8077"
        },
        "2022-06-07 17:25:00": {
            "1. open": "122.6523",
            "2. high": "122.7400",
            "3. low": "122.6500",
            "4. close": "122.6800",
            "5. volume": "5358"
        },
        "2022-06-07 17:20:00": {
            "1. open": "122.6900",
            "2. high": "122.7000",
            "3. low": "122.6700",
            "4. close": "122.6800",
            "5. volume": "6097"
        },
        "2022-06-07 17:15:00": {
            "1. open": "122.7000",
            "2. high": "122.7000",
            "3. low": "122.6200",
            "4. close": "122.6900",
            "5. volume": "8732"
        },
        "2022-06-07 17:10:00": {
            "1. open": "122.6512",
            "2. high": "122.6600",
            "3. low": "122.6000",
            "4. close": "122.6500",
            "5. volume": "6197"
        },
        "2022-06-07 17:05:00": {
            "1. open": "122.6600",
            "2. high": "122.7000",
            "3. low": "122.6300",
            "4. close": "122.6900",
            "5. volume": "8554"
        },
        "2022-06-07 17:00:00": {
            "1. open": "122.7388",
            "2. high": "122.7388",
            "3. low": "122.6600",
            "4. close": "122.6600",
            "5. volume": "11062"
        },
        "2022-06-07 16:55:00": {
            "1. open": "122.6700",
            "2. high": "122.7500",
            "3. low": "122.6500",
            "4. close": "122.6900",
            "5. volume": "4370"
        },
        "2022-06-07 16:50:00": {
            "1. open": "122.6300",
            "2. high": "122.6700",
            "3. low": "122.5901",
            "4. close": "122.6300",
            "5. volume": "9260"
        },
        "2022-06-07 16:45:00": {
            "1. open": "122.6500",
            "2. high": "122.6500",
            "3. low": "122.6000",
            "4. close": "122.6299",
            "5. volume": "10569"
        },
        "2022-06-07 16:40:00": {
            "1. open": "122.6400",
            "2. high": "122.6900",
            "3. low": "122.5900",
            "4. close": "122.6500",
            "5. volume": "7455"
        },
        "2022-06-07 16:35:00": {
            "1. open": "122.8370",
            "2. high": "122.8370",
            "3. low": "122.6100",
            "4. close": "122.6309",
            "5. volume": "15464"
        },
        "2022-06-07 16:30:00": {
            "1. open": "122.9100",
            "2. high": "123.0000",
            "3. low": "122.8000",
            "4. close": "122.8000",
            "5. volume": "19605"
        },
        "2022-06-07 16:25:00": {
            "1. open": "122.8512",
            "2. high": "122.9500",
            "3. low": "122.8500",
            "4. close": "122.8500",
            "5. volume": "9945"
        },
        "2022-06-07 16:20:00": {
            "1. open": "122.8200",
            "2. high": "123.0000",
            "3. low": "122.8000",
            "4. close": "122.9462",
            "5. volume": "56982"
        },
        "2022-06-07 16:15:00": {
            "1. open": "123.0000",
            "2. high": "123.0000",
            "3. low": "122.8040",
            "4. close": "122.8200",
            "5. volume": "62498"
        },
        "2022-06-07 16:10:00": {
            "1. open": "122.8024",
            "2. high": "123.0000",
            "3. low": "122.7600",
            "4. close": "122.9001",
            "5. volume": "94266"
        },
        "2022-06-07 16:05:00": {
            "1. open": "123.0000",
            "2. high": "123.0000",
            "3. low": "122.8000",
            "4. close": "122.8800",
            "5. volume": "662896"
        },
        "2022-06-07 16:00:00": {
            "1. open": "123.3500",
            "2. high": "123.3900",
            "3. low": "122.9900",
            "4. close": "123.0000",
            "5. volume": "2077700"
        },
        "2022-06-07 15:55:00": {
            "1. open": "123.2200",
            "2. high": "123.5600",
            "3. low": "123.0600",
            "4. close": "123.3100",
            "5. volume": "1632510"
        },
        "2022-06-07 15:50:00": {
            "1. open": "122.8350",
            "2. high": "123.3000",
            "3. low": "122.8300",
            "4. close": "123.2300",
            "5. volume": "960747"
        },
        "2022-06-07 15:45:00": {
            "1. open": "123.0805",
            "2. high": "123.1500",
            "3. low": "122.7300",
            "4. close": "122.8499",
            "5. volume": "859535"
        },
        "2022-06-07 15:40:00": {
            "1. open": "122.9300",
            "2. high": "123.2300",
            "3. low": "122.8408",
            "4. close": "123.0805",
            "5. volume": "847713"
        },
        "2022-06-07 15:35:00": {
            "1. open": "122.6800",
            "2. high": "122.9500",
            "3. low": "122.4450",
            "4. close": "122.9308",
            "5. volume": "724277"
        },
        "2022-06-07 15:30:00": {
            "1. open": "122.5500",
            "2. high": "122.6750",
            "3. low": "122.3400",
            "4. close": "122.6700",
            "5. volume": "532734"
        },
        "2022-06-07 15:25:00": {
            "1. open": "122.5800",
            "2. high": "122.7300",
            "3. low": "122.5000",
            "4. close": "122.5500",
            "5. volume": "518054"
        },
        "2022-06-07 15:20:00": {
            "1. open": "122.5389",
            "2. high": "122.6699",
            "3. low": "122.5000",
            "4. close": "122.5841",
            "5. volume": "485323"
        },
        "2022-06-07 15:15:00": {
            "1. open": "122.7200",
            "2. high": "122.8000",
            "3. low": "122.4000",
            "4. close": "122.5350",
            "5. volume": "658281"
        },
        "2022-06-07 15:10:00": {
            "1. open": "122.6479",
            "2. high": "122.8700",
            "3. low": "122.6000",
            "4. close": "122.7130",
            "5. volume": "674434"
        },
        "2022-06-07 15:05:00": {
            "1. open": "122.1810",
            "2. high": "122.7300",
            "3. low": "122.1600",
            "4. close": "122.6400",
            "5. volume": "771766"
        },
        "2022-06-07 15:00:00": {
            "1. open": "122.1100",
            "2. high": "122.3100",
            "3. low": "122.0510",
            "4. close": "122.1800",
            "5. volume": "498786"
        },
        "2022-06-07 14:55:00": {
            "1. open": "122.1350",
            "2. high": "122.2500",
            "3. low": "122.0700",
            "4. close": "122.1007",
            "5. volume": "508177"
        },
        "2022-06-07 14:50:00": {
            "1. open": "122.1350",
            "2. high": "122.3000",
            "3. low": "121.9400",
            "4. close": "122.1360",
            "5. volume": "569405"
        },
        "2022-06-07 14:45:00": {
            "1. open": "122.7025",
            "2. high": "122.7100",
            "3. low": "122.0767",
            "4. close": "122.1350",
            "5. volume": "785495"
        },
        "2022-06-07 14:40:00": {
            "1. open": "122.7800",
            "2. high": "122.8100",
            "3. low": "122.6325",
            "4. close": "122.7000",
            "5. volume": "469276"
        },
        "2022-06-07 14:35:00": {
            "1. open": "122.7400",
            "2. high": "122.8100",
            "3. low": "122.6700",
            "4. close": "122.7900",
            "5. volume": "473038"
        },
        "2022-06-07 14:30:00": {
            "1. open": "122.6818",
            "2. high": "122.8100",
            "3. low": "122.5810",
            "4. close": "122.7450",
            "5. volume": "521687"
        },
        "2022-06-07 14:25:00": {
            "1. open": "122.4100",
            "2. high": "122.6900",
            "3. low": "122.3900",
            "4. close": "122.6800",
            "5. volume": "400122"
        },
        "2022-06-07 14:20:00": {
            "1. open": "122.6312",
            "2. high": "122.7600",
            "3. low": "122.3800",
            "4. close": "122.3910",
            "5. volume": "591478"
        },
        "2022-06-07 14:15:00": {
            "1. open": "122.6600",
            "2. high": "122.7599",
            "3. low": "122.4200",
            "4. close": "122.6350",
            "5. volume": "700613"
        },
        "2022-06-07 14:10:00": {
            "1. open": "122.2600",
            "2. high": "122.7400",
            "3. low": "122.1918",
            "4. close": "122.6396",
            "5. volume": "698468"
        },
        "2022-06-07 14:05:00": {
            "1. open": "122.0900",
            "2. high": "122.2900",
            "3. low": "122.0101",
            "4. close": "122.2600",
            "5. volume": "740390"
        },
        "2022-06-07 14:00:00": {
            "1. open": "122.0500",
            "2. high": "122.2000",
            "3. low": "121.9400",
            "4. close": "122.0880",
            "5. volume": "449294"
        },
        "2022-06-07 13:55:00": {
            "1. open": "121.9700",
            "2. high": "122.2249",
            "3. low": "121.8900",
            "4. close": "122.0542",
            "5. volume": "511613"
        },
        "2022-06-07 13:50:00": {
            "1. open": "121.9600",
            "2. high": "122.1700",
            "3. low": "121.8500",
            "4. close": "121.9625",
            "5. volume": "509376"
        },
        "2022-06-07 13:45:00": {
            "1. open": "122.1301",
            "2. high": "122.1616",
            "3. low": "121.7578",
            "4. close": "121.9600",
            "5. volume": "493162"
        },
        "2022-06-07 13:40:00": {
            "1. open": "122.2100",
            "2. high": "122.2800",
            "3. low": "122.0000",
            "4. close": "122.1191",
            "5. volume": "371849"
        },
        "2022-06-07 13:35:00": {
            "1. open": "122.0200",
            "2. high": "122.2800",
            "3. low": "121.9500",
            "4. close": "122.2200",
            "5. volume": "416104"
        },
        "2022-06-07 13:30:00": {
            "1. open": "122.1500",
            "2. high": "122.1800",
            "3. low": "121.9354",
            "4. close": "121.9900",
            "5. volume": "451673"
        },
        "2022-06-07 13:25:00": {
            "1. open": "122.3300",
            "2. high": "122.4800",
            "3. low": "122.1000",
            "4. close": "122.1400",
            "5. volume": "489501"
        },
        "2022-06-07 13:20:00": {
            "1. open": "122.0100",
            "2. high": "122.4199",
            "3. low": "122.0000",
            "4. close": "122.3200",
            "5. volume": "611181"
        },
        "2022-06-07 13:15:00": {
            "1. open": "122.1100",
            "2. high": "122.1800",
            "3. low": "121.9200",
            "4. close": "122.0200",
            "5. volume": "641807"
        },
        "2022-06-07 13:10:00": {
            "1. open": "121.8500",
            "2. high": "122.1300",
            "3. low": "121.8200",
            "4. close": "122.1094",
            "5. volume": "719279"
        },
        "2022-06-07 13:05:00": {
            "1. open": "121.6700",
            "2. high": "121.8999",
            "3. low": "121.4000",
            "4. close": "121.8674",
            "5. volume": "553113"
        },
        "2022-06-07 13:00:00": {
            "1. open": "121.8301",
            "2. high": "121.8400",
            "3. low": "121.5100",
            "4. close": "121.6700",
            "5. volume": "441325"
        },
        "2022-06-07 12:55:00": {
            "1. open": "121.7283",
            "2. high": "121.9000",
            "3. low": "121.4600",
            "4. close": "121.8200",
            "5. volume": "745572"
        },
        "2022-06-07 12:50:00": {
            "1. open": "121.5650",
            "2. high": "121.7900",
            "3. low": "121.5400",
            "4. close": "121.7209",
            "5. volume": "435152"
        },
        "2022-06-07 12:45:00": {
            "1. open": "121.5000",
            "2. high": "121.8000",
            "3. low": "121.4600",
            "4. close": "121.5662",
            "5. volume": "754864"
        },
        "2022-06-07 12:40:00": {
            "1. open": "121.3700",
            "2. high": "121.5200",
            "3. low": "121.1900",
            "4. close": "121.4847",
            "5. volume": "635655"
        },
        "2022-06-07 12:35:00": {
            "1. open": "121.2700",
            "2. high": "121.5400",
            "3. low": "121.0200",
            "4. close": "121.3700",
            "5. volume": "1006024"
        },
        "2022-06-07 12:30:00": {
            "1. open": "121.7300",
            "2. high": "121.7700",
            "3. low": "121.2600",
            "4. close": "121.2700",
            "5. volume": "1035879"
        },
        "2022-06-07 12:25:00": {
            "1. open": "121.9500",
            "2. high": "121.9550",
            "3. low": "121.7000",
            "4. close": "121.7350",
            "5. volume": "489296"
        },
        "2022-06-07 12:20:00": {
            "1. open": "121.9000",
            "2. high": "122.0600",
            "3. low": "121.5100",
            "4. close": "121.9600",
            "5. volume": "770521"
        },
        "2022-06-07 12:15:00": {
            "1. open": "122.0000",
            "2. high": "122.0900",
            "3. low": "121.8900",
            "4. close": "121.9100",
            "5. volume": "413981"
        },
        "2022-06-07 12:10:00": {
            "1. open": "122.0647",
            "2. high": "122.0900",
            "3. low": "121.8000",
            "4. close": "121.9800",
            "5. volume": "580512"
        },
        "2022-06-07 12:05:00": {
            "1. open": "122.4600",
            "2. high": "122.5000",
            "3. low": "122.0200",
            "4. close": "122.0785",
            "5. volume": "557529"
        },
        "2022-06-07 12:00:00": {
            "1. open": "121.9300",
            "2. high": "122.6300",
            "3. low": "121.9100",
            "4. close": "122.4170",
            "5. volume": "973576"
        },
        "2022-06-07 11:55:00": {
            "1. open": "121.6700",
            "2. high": "122.1200",
            "3. low": "121.5744",
            "4. close": "121.9600",
            "5. volume": "736294"
        },
        "2022-06-07 11:50:00": {
            "1. open": "122.0200",
            "2. high": "122.3500",
            "3. low": "121.6000",
            "4. close": "121.6700",
            "5. volume": "925985"
        },
        "2022-06-07 11:45:00": {
            "1. open": "122.0999",
            "2. high": "122.1023",
            "3. low": "121.7300",
            "4. close": "122.0048",
            "5. volume": "673891"
        }
    }
}